PyNucleus/__init__.py
PyNucleus/__main__.py
PyNucleus/calculator.py
PyNucleus/commands.py
PyNucleus/decorators.py
PyNucleus/errors.py
PyNucleus/functions.py
PyNucleus/memory.py
PyNucleus-0.0.3.dist-info/LICENSE
PyNucleus-0.0.3.dist-info/METADATA
PyNucleus-0.0.3.dist-info/WHEEL
PyNucleus-0.0.3.dist-info/top_level.txt
PyNucleus-0.0.3.dist-info/RECORD
