Metadata-Version: 2.1
Name: PyNucleus
Version: 0.0.3
Summary: Essential Python Toolkit.
License-File: LICENSE
